mark_cont_area/__init__.py
mark_cont_area/fill_only1gap.py
mark_cont_area/mark_cont_area.py
mark_cont_area-1.1.1.dist-info/LICENSE
mark_cont_area-1.1.1.dist-info/METADATA
mark_cont_area-1.1.1.dist-info/WHEEL
mark_cont_area-1.1.1.dist-info/top_level.txt
mark_cont_area-1.1.1.dist-info/RECORD
