Metadata-Version: 2.1
Name: mark_cont_area
Version: 1.1.1
Summary: Mark continuous areas with positive natural numbers (1,2,3,...,N)
Author: Mingxi Zhang
Author-email: zhang.mingxi@outlook.com
License-File: LICENSE
